LICENSE
README.md
setup.py
bin/eva4-svc-controller-py
eva4_controller_py/__init__.py
eva4_controller_py/macro_api.py
eva4_controller_py/macro_builtins.py
eva4_controller_py.egg-info/PKG-INFO
eva4_controller_py.egg-info/SOURCES.txt
eva4_controller_py.egg-info/dependency_links.txt
eva4_controller_py.egg-info/requires.txt
eva4_controller_py.egg-info/top_level.txt